ccalogging/__init__.py
ccalogging-0.5.3.dist-info/LICENSE
ccalogging-0.5.3.dist-info/METADATA
ccalogging-0.5.3.dist-info/WHEEL
ccalogging-0.5.3.dist-info/RECORD
