Metadata-Version: 2.1
Name: ccalogging
Version: 0.5.3
Summary: Simple logging
License: GPL 3
Author: ccdale
Author-email: chris.charles.allison+ccalogging@gmail.com
Requires-Python: >=3.8,<4.0
Classifier: License :: Other/Proprietary License
Classifier: Programming Language :: Python :: 3
Classifier: Programming Language :: Python :: 3.8
Classifier: Programming Language :: Python :: 3.9
Classifier: Programming Language :: Python :: 3.10
Classifier: Programming Language :: Python :: 3.11
Classifier: Programming Language :: Python :: 3.12
